{"rushing":{"2018":{"gamesPlayed":"10","rushingAttempts":"2","rushingYards":"2","yardsPerRushAttempt":"1.0","rushingTouchdowns":"0","longRushing":"5","rushingFirstDowns":"0","rushingFumbles":"0","rushingFumblesLost":"0"},"2019":{"gamesPlayed":"12","rushingAttempts":"3","rushingYards":"10","yardsPerRushAttempt":"3.3","rushingTouchdowns":"0","longRushing":"6","rushingFirstDowns":"0","rushingFumbles":"0","rushingFumblesLost":"0"}},"passing":{},"receiving":{"2018":{"gamesPlayed":"10","receptions":"7","receivingTargets":"7","receivingYards":"37","yardsPerReception":"5.3","receivingTouchdowns":"0","longReception":"17","receivingFirstDowns":"1","receivingFumbles":"0","receivingFumblesLost":"0"},"2019":{"gamesPlayed":"12","receptions":"2","receivingTargets":"3","receivingYards":"13","yardsPerReception":"6.5","receivingTouchdowns":"0","longReception":"11","receivingFirstDowns":"1","receivingFumbles":"0","receivingFumblesLost":"0"}},"scoring":{}}